xad/__init__.py
xad/__init__.pyi
xad/_xad/__init__.pyi
xad/_xad/adj_1st.pyi
xad/_xad/exceptions.pyi
xad/_xad/fwd_1st.pyi
xad/_xad/math.pyi
xad/_xad.cp38-win_amd64.pyd
xad/adj_1st/__init__.py
xad/exceptions/__init__.py
xad/fwd_1st/__init__.py
xad/math/__init__.py
xad-1.5.2.dist-info/METADATA
xad-1.5.2.dist-info/WHEEL
xad-1.5.2.dist-info/RECORD
