Metadata-Version: 2.1
Name: xad
Version: 1.5.2
Summary: High-Performance Automatic Differentiation for Python
Home-page: https://auto-differentiation.github.io
License: AGPL-3.0-or-later
Keywords: automatic-differentiation,derivatives,machine-learning,optimisation,numerical-analysis,scientific-computing,risk-management,computer-graphics,robotics,biotechnology,meteorology,quant-finance
Author: Auto Differentiation Dev Team
Author-email: dev@auto-differentiation.com
Requires-Python: >=3.8.1,<4.0
Classifier: Development Status :: 5 - Production/Stable
Classifier: Intended Audience :: Developers
Classifier: Intended Audience :: Education
Classifier: Intended Audience :: Financial and Insurance Industry
Classifier: Intended Audience :: Science/Research
Classifier: License :: OSI Approved :: GNU Affero General Public License v3 or later (AGPLv3+)
Classifier: License :: Other/Proprietary License
Classifier: Natural Language :: English
Classifier: Operating System :: MacOS :: MacOS X
Classifier: Operating System :: Microsoft :: Windows
Classifier: Operating System :: POSIX :: Linux
Classifier: Programming Language :: Python :: 3
Classifier: Programming Language :: Python :: 3.9
Classifier: Programming Language :: Python :: 3.10
Classifier: Programming Language :: Python :: 3.11
Classifier: Programming Language :: Python :: 3.12
Classifier: Programming Language :: Python :: 3.8
Classifier: Programming Language :: Python :: Implementation :: CPython
Classifier: Topic :: Scientific/Engineering
Classifier: Topic :: Software Development
Project-URL: Documentation, https://auto-differentiation.github.io/tutorials/python
Project-URL: Download, https://pypi.org/project/xad/#files
Project-URL: Repository, https://github.com/auto-differentiation/xad-py
Project-URL: Release notes, https://github.com/auto-differentiation/xad-py/releases
Project-URL: Tracker, https://github.com/auto-differentiation/xad-py/issues
